reflectee/__init__.py
reflectee/server.py
reflectee/core/encoder.py
reflectee/core/event.py
reflectee/core/exceptions.py
reflectee/core/handlers.py
reflectee/core/reflect.py
reflectee/core/register.py
reflectee/core/require.py
reflectee/core/serializers.py
reflectee/core/session.py
reflectee/core/sessions.py
reflectee/django/__init__.py
reflectee/django/apps.py
reflectee/django/asgi.py
reflectee/django/event.py
reflectee/django/session.py
reflectee/django/wsgi.py
reflectee/django/management/commands/reflectee_test.py
reflectee/django/management/commands/runserver.py
reflectee/utils/__init__.py
reflectee/utils/forms.py
reflectee/utils/pagination.py
reflectee/utils/stringcase.py
reflectee-1.0.2.dist-info/METADATA
reflectee-1.0.2.dist-info/WHEEL
reflectee-1.0.2.dist-info/top_level.txt
reflectee-1.0.2.dist-info/RECORD
